[
  {
    "name": "ablation-planner",
    "title": "Ablation Study Planner",
    "description": "Use this skill to design reviewer-oriented ablation studies that test which components, assumptions, or design choices support a paper's claims.",
    "skill_path": "ablation-planner/SKILL.md",
    "triggers": [
      "ablation study",
      "ablation planner",
      "design ablations",
      "component analysis",
      "消融实验",
      "设计消融",
      "模块消融",
      "实验补充",
      "reviewer asks ablation",
      "claim validation",
      "variant comparison",
      "remove component"
    ],
    "references": []
  },
  {
    "name": "analyze-results",
    "title": "Experiment Results Analysis",
    "description": "Use this skill to interpret machine learning experiment results, compare methods, summarize metrics, and produce evidence-aware tables or insights.",
    "skill_path": "analyze-results/SKILL.md",
    "triggers": [
      "analyze results",
      "compare results",
      "experiment results",
      "metrics analysis",
      "结果分析",
      "实验结果",
      "对比实验",
      "指标分析",
      "performance table",
      "statistical comparison",
      "benchmark comparison",
      "结果怎么解释"
    ],
    "references": []
  },
  {
    "name": "claims-drafting",
    "title": "Patent Claims Drafting",
    "description": "Use this skill to draft patent claims from an invention disclosure or technical idea.",
    "skill_path": "claims-drafting/SKILL.md",
    "triggers": [
      "draft claims",
      "claim drafting",
      "patent claims",
      "independent claim",
      "撰写权利要求",
      "写权利要求书",
      "权利要求",
      "独立权利要求",
      "dependent claims",
      "claim scope",
      "专利权利要求",
      "claim set"
    ],
    "references": []
  },
  {
    "name": "codex-index-generator",
    "title": "Codex Skill Index Generator",
    "description": "Use this skill locally in Codex to update skills/index.json while preserving existing entries and generating metadata only for new skills.",
    "skill_path": "codex-index-generator/SKILL.md",
    "triggers": [
      "generate skill index",
      "update skills index",
      "index.json",
      "Personal Skills MCP",
      "Codex index",
      "skill manifest",
      "生成index",
      "更新index",
      "技能索引",
      "维护skills",
      "新增skill索引",
      "更新技能列表"
    ],
    "references": []
  },
  {
    "name": "deep-research",
    "title": "Deep Academic Research",
    "description": "Use this skill for thorough multi-source literature investigation, fact verification, PDF deep reading, and structured evidence audits.",
    "skill_path": "deep-research/SKILL.md",
    "triggers": [
      "deep research",
      "deep dive",
      "thorough investigation",
      "multi-source verification",
      "深入研究",
      "深度调研",
      "深入核查",
      "全面核查",
      "事实核查",
      "深挖",
      "系统调查",
      "evidence audit",
      "cross-source verification",
      "深入检索"
    ],
    "references": []
  },
  {
    "name": "embodiment-description",
    "title": "Patent Embodiment Description",
    "description": "Use this skill to write detailed embodiments that explain how to practice an invention in a patent specification.",
    "skill_path": "embodiment-description/SKILL.md",
    "triggers": [
      "write embodiment",
      "embodiment description",
      "detailed description",
      "patent embodiment",
      "撰写实施例",
      "实施例描述",
      "具体实施方式",
      "专利实施例",
      "how to practice invention",
      "implementation example",
      "technical embodiment",
      "实施方式"
    ],
    "references": []
  },
  {
    "name": "experiment-audit",
    "title": "Experiment Integrity Audit",
    "description": "Use this skill to audit whether experiments honestly support claimed results and to detect missing evidence, invalid comparisons, or result-reporting risks.",
    "skill_path": "experiment-audit/SKILL.md",
    "triggers": [
      "experiment audit",
      "audit results",
      "experiment integrity",
      "check experiment validity",
      "审计实验",
      "实验审计",
      "实验诚实度",
      "结果核查",
      "fake ground truth",
      "score normalization",
      "phantom results",
      "claim support check",
      "实验是否支撑结论",
      "submission check"
    ],
    "references": []
  },
  {
    "name": "experiment-plan",
    "title": "Claim-Driven Experiment Plan",
    "description": "Use this skill to turn a research idea or refined method into a detailed experiment roadmap, evaluation protocol, ablation matrix, and compute-aware run plan.",
    "skill_path": "experiment-plan/SKILL.md",
    "triggers": [
      "experiment plan",
      "evaluation protocol",
      "run order",
      "compute budget",
      "实验计划",
      "实验设计",
      "评测方案",
      "实验路线",
      "ablation matrix",
      "baseline selection",
      "dataset selection",
      "指标设计",
      "paper-ready validation",
      "怎么做实验"
    ],
    "references": []
  },
  {
    "name": "figure-description",
    "title": "Patent Figure Description",
    "description": "Use this skill to turn patent figures or figure lists into formal drawing descriptions with reference numerals.",
    "skill_path": "figure-description/SKILL.md",
    "triggers": [
      "figure description",
      "drawing description",
      "patent figures",
      "reference numerals",
      "附图说明",
      "附图处理",
      "专利附图",
      "图示说明",
      "drawings description",
      "figure list",
      "reference number",
      "附图标记"
    ],
    "references": []
  },
  {
    "name": "formula-derivation",
    "title": "Formula Derivation",
    "description": "Use this skill to structure assumptions, derive formulas, organize equations, and turn theory notes into a coherent research derivation.",
    "skill_path": "formula-derivation/SKILL.md",
    "triggers": [
      "formula derivation",
      "derive equation",
      "theory line",
      "mathematical derivation",
      "推导公式",
      "公式推导",
      "理论推导",
      "整理公式",
      "assumptions",
      "equation organization",
      "derivation package",
      "数学建模",
      "paper-ready derivation",
      "理论线"
    ],
    "references": []
  },
  {
    "name": "idea-creator",
    "title": "Research Idea Creator",
    "description": "Use this skill to brainstorm, generate, and rank publishable research ideas within a broad direction.",
    "skill_path": "idea-creator/SKILL.md",
    "triggers": [
      "generate research ideas",
      "brainstorm ideas",
      "find research idea",
      "what can we work on",
      "找idea",
      "研究idea",
      "想研究方向",
      "头脑风暴",
      "publishable directions",
      "idea ranking",
      "new method idea",
      "选题",
      "research brainstorming",
      "创新点"
    ],
    "references": []
  },
  {
    "name": "invention-structuring",
    "title": "Invention Disclosure Structuring",
    "description": "Use this skill to structure a raw technical idea into a patent-ready invention disclosure.",
    "skill_path": "invention-structuring/SKILL.md",
    "triggers": [
      "invention disclosure",
      "structure invention",
      "patent-ready invention",
      "technical solution",
      "构建发明",
      "发明构建",
      "发明交底",
      "技术方案",
      "formalize invention",
      "inventive concept",
      "发明点",
      "专利交底"
    ],
    "references": []
  },
  {
    "name": "mermaid-diagram",
    "title": "Mermaid Diagram Generator",
    "description": "Use this skill to generate Mermaid diagram code for flowcharts, sequence diagrams, class diagrams, ER diagrams, Gantt charts, and related diagrams.",
    "skill_path": "mermaid-diagram/SKILL.md",
    "triggers": [
      "Mermaid diagram",
      "flowchart",
      "sequence diagram",
      "class diagram",
      "mermaid图",
      "流程图",
      "时序图",
      "类图",
      "ER diagram",
      "Gantt chart",
      "diagram code",
      "画图代码",
      "architecture flowchart",
      "系统流程图"
    ],
    "references": []
  },
  {
    "name": "novelty-check",
    "title": "Research Novelty Check",
    "description": "Use this skill to check whether a research idea or method appears novel against recent literature and known approaches.",
    "skill_path": "novelty-check/SKILL.md",
    "triggers": [
      "novelty check",
      "check novelty",
      "has anyone done this",
      "prior work check",
      "查新",
      "有没有人做过",
      "创新性检查",
      "新颖性",
      "research idea novelty",
      "method already done",
      "文献查重",
      "相关方法",
      "novel contribution",
      "是否有创新"
    ],
    "references": []
  },
  {
    "name": "paper-claim-audit",
    "title": "Paper Claim Audit",
    "description": "Use this skill to verify that a paper's numerical results, comparisons, and scope claims match the available evidence.",
    "skill_path": "paper-claim-audit/SKILL.md",
    "triggers": [
      "paper claim audit",
      "check paper claims",
      "verify numbers",
      "claim verification",
      "审查论文数据",
      "论文数字核对",
      "核对结果",
      "检查论文claim",
      "paper-to-evidence",
      "submission audit",
      "number mismatch",
      "结果是否一致",
      "scope claim",
      "证据核查"
    ],
    "references": []
  },
  {
    "name": "paper-figure",
    "title": "Web-Safe Paper Figure Planner",
    "description": "Use this skill to plan publication-quality paper figures, plots, tables, captions, and visualization specifications from experimental results.",
    "skill_path": "paper-figure/SKILL.md",
    "triggers": [
      "paper figure",
      "paper figures",
      "figure plan",
      "plot",
      "论文图",
      "论文图表",
      "作图",
      "画图",
      "visualization",
      "result table",
      "caption",
      "实验结果可视化",
      "figure specification",
      "图表规划"
    ],
    "references": []
  },
  {
    "name": "paper-illustration",
    "title": "Web-Safe Paper Illustration Designer",
    "description": "Use this skill to design method diagrams, architecture figures, visual abstracts, and image-generation prompts for academic papers.",
    "skill_path": "paper-illustration/SKILL.md",
    "triggers": [
      "paper illustration",
      "method diagram",
      "architecture diagram",
      "framework figure",
      "论文插图",
      "方法图",
      "架构图",
      "机制图",
      "visual abstract",
      "conceptual illustration",
      "image prompt",
      "示意图",
      "pipeline figure",
      "画架构图"
    ],
    "references": []
  },
  {
    "name": "paper-plan",
    "title": "Paper Outline Planner",
    "description": "Use this skill to generate a structured paper outline from a topic, narrative, review conclusions, or experiment results.",
    "skill_path": "paper-plan/SKILL.md",
    "triggers": [
      "paper outline",
      "plan the paper",
      "paper plan",
      "section outline",
      "写大纲",
      "论文规划",
      "论文大纲",
      "文章结构",
      "narrative structure",
      "paper organization",
      "section plan",
      "投稿论文规划",
      "from results to paper",
      "怎么组织论文"
    ],
    "references": []
  },
  {
    "name": "paper-poster",
    "title": "Web-Safe Paper Poster Planner",
    "description": "Use this skill to convert a paper or research project into a conference poster layout, section text, figure placement plan, captions, and presenter pitch.",
    "skill_path": "paper-poster/SKILL.md",
    "triggers": [
      "paper poster",
      "conference poster",
      "academic poster",
      "poster layout",
      "海报",
      "学术海报",
      "会议海报",
      "poster设计",
      "poster content",
      "poster pitch",
      "poster sections",
      "展示海报",
      "figure placement",
      "poster presentation"
    ],
    "references": []
  },
  {
    "name": "paper-slides",
    "title": "Web-Safe Paper Slides Planner",
    "description": "Use this skill to convert a paper, abstract, or research project into a conference-talk slide outline, speaker notes, and talk script.",
    "skill_path": "paper-slides/SKILL.md",
    "triggers": [
      "paper slides",
      "presentation",
      "conference talk",
      "talk script",
      "幻灯片",
      "做PPT",
      "演讲稿",
      "汇报",
      "speaker notes",
      "slides outline",
      "答辩",
      "presentation plan",
      "paper presentation",
      "会议汇报"
    ],
    "references": []
  },
  {
    "name": "paper-write",
    "title": "Paper Section Writer",
    "description": "Use this skill to draft LaTeX paper sections from a paper plan, outline, venue target, or section-level writing goal.",
    "skill_path": "paper-write/SKILL.md",
    "triggers": [
      "write paper",
      "draft LaTeX",
      "paper section",
      "paper writing",
      "写论文",
      "开始写",
      "论文写作",
      "LaTeX论文",
      "draft introduction",
      "draft method",
      "draft experiments",
      "章节撰写",
      "conference paper",
      "论文初稿"
    ],
    "references": []
  },
  {
    "name": "patent-review",
    "title": "Web-Safe Patent Review",
    "description": "Use this skill to simulate a patent examiner-style review of claims, specification, embodiments, figures, and prior-art risks.",
    "skill_path": "patent-review/SKILL.md",
    "triggers": [
      "patent review",
      "examiner review",
      "office action",
      "patent examiner",
      "专利审查",
      "审查意见",
      "权利要求审查",
      "新颖性",
      "claims review",
      "inventive step",
      "enablement",
      "说明书",
      "prior art risk",
      "创造性"
    ],
    "references": []
  },
  {
    "name": "quick-lit",
    "title": "Quick Literature Search",
    "description": "Use this skill for fast academic literature search, source tracing, related-work mapping, paper summaries, or material-property source lookup.",
    "skill_path": "quick-lit/SKILL.md",
    "triggers": [
      "literature search",
      "quick literature search",
      "find papers",
      "source tracing",
      "文献检索",
      "查文献",
      "找论文",
      "搜论文",
      "相关工作",
      "文献来源",
      "论文来源",
      "参考文献来源",
      "material properties",
      "物性参数",
      "查热导率",
      "查比热"
    ],
    "references": []
  },
  {
    "name": "rebuttal",
    "title": "Review Rebuttal Writer",
    "description": "Use this skill to prepare grounded, venue-compliant rebuttal responses to external reviews.",
    "skill_path": "rebuttal/SKILL.md",
    "triggers": [
      "rebuttal",
      "reply to reviewers",
      "review response",
      "OpenReview response",
      "审稿回复",
      "回复审稿人",
      "rebuttal写作",
      "审稿意见回复",
      "ICML rebuttal",
      "NeurIPS rebuttal",
      "review coverage",
      "反驳审稿意见",
      "response letter",
      "逐条回复"
    ],
    "references": []
  },
  {
    "name": "research-lit",
    "title": "Research Literature Review",
    "description": "Use this skill to search, summarize, and analyze academic papers for related work or literature review tasks.",
    "skill_path": "research-lit/SKILL.md",
    "triggers": [
      "literature review",
      "related work",
      "research papers",
      "find related papers",
      "文献综述",
      "相关工作",
      "论文总结",
      "读论文",
      "what does this paper say",
      "paper summary",
      "survey papers",
      "研究文献",
      "paper analysis",
      "梳理文献"
    ],
    "references": []
  },
  {
    "name": "research-refine",
    "title": "Research Plan Refinement",
    "description": "Use this skill to turn a vague research direction into a concrete, problem-anchored, implementation-oriented method plan.",
    "skill_path": "research-refine/SKILL.md",
    "triggers": [
      "refine research plan",
      "refine my approach",
      "decompose this problem",
      "method plan",
      "细化研究方案",
      "打磨idea",
      "细化方案",
      "分解问题",
      "research direction refinement",
      "concrete method",
      "top-venue ready",
      "方法设计",
      "problem-anchored plan",
      "方案收敛"
    ],
    "references": []
  },
  {
    "name": "research-review",
    "title": "Web-Safe Research Review",
    "description": "Use this skill to critically review a research idea, paper draft, experiment plan, or results from the perspective of senior academic reviewers.",
    "skill_path": "research-review/SKILL.md",
    "triggers": [
      "research review",
      "review my research",
      "idea review",
      "external review",
      "研究审阅",
      "帮我review",
      "评审",
      "批判性分析",
      "reviewer comments",
      "critique",
      "experiment plan review",
      "研究方案评审",
      "claim matrix",
      "top-venue readiness"
    ],
    "references": []
  },
  {
    "name": "result-to-claim",
    "title": "Result-to-Claim Gate",
    "description": "Use this skill after experiments finish to judge what claims the results support, what remains unsupported, and what evidence is still needed.",
    "skill_path": "result-to-claim/SKILL.md",
    "triggers": [
      "result to claim",
      "what claims are supported",
      "claim support",
      "after experiments",
      "结果支持什么结论",
      "实验结果能说明什么",
      "结论判断",
      "是否能写claim",
      "evidence missing",
      "claim_supported",
      "partial support",
      "补实验还是改结论",
      "paper claims from results",
      "结果解释"
    ],
    "references": []
  },
  {
    "name": "specification-writing",
    "title": "Patent Specification Writing",
    "description": "Use this skill to write a full patent specification from claims, embodiments, and invention disclosure materials.",
    "skill_path": "specification-writing/SKILL.md",
    "triggers": [
      "write specification",
      "patent specification",
      "patent description",
      "complete patent draft",
      "撰写说明书",
      "写说明书",
      "专利说明书",
      "完整专利文本",
      "technical field",
      "background art",
      "summary of invention",
      "具体实施方式",
      "description drafting",
      "专利撰写"
    ],
    "references": []
  },
  {
    "name": "writing-systems-papers",
    "title": "Systems Paper Writing Blueprint",
    "description": "Use this skill for paragraph-level structure, page allocation, and writing patterns for systems papers targeting venues such as OSDI, SOSP, ASPLOS, NSDI, and EuroSys.",
    "skill_path": "writing-systems-papers/SKILL.md",
    "triggers": [
      "systems paper",
      "OSDI paper",
      "SOSP paper",
      "NSDI paper",
      "写系统论文",
      "系统论文结构",
      "系统会议论文",
      "段落结构",
      "ASPLOS",
      "EuroSys",
      "page allocation",
      "paragraph template",
      "systems writing",
      "论文结构蓝图"
    ],
    "references": []
  }
]
